antarctic_plots/__init__.py
polartoolkit/__init__.py
polartoolkit/_version.py
polartoolkit/_version.pyi
polartoolkit/fetch.py
polartoolkit/maps.py
polartoolkit/profile.py
polartoolkit/profiles.py
polartoolkit/regions.py
polartoolkit/utils.py
polartoolkit-1.4.0.dist-info/METADATA
polartoolkit-1.4.0.dist-info/WHEEL
polartoolkit-1.4.0.dist-info/licenses/AUTHORS.md
polartoolkit-1.4.0.dist-info/licenses/LICENSE
polartoolkit-1.4.0.dist-info/RECORD
