Metadata-Version: 2.4
Name: polartoolkit
Version: 1.4.0
Summary: Helpful tools for polar researchers
Project-URL: Homepage, https://github.com/mdtanker/polartoolkit
Project-URL: Documentation, https://polartoolkit.readthedocs.io/
Project-URL: Bug Tracker, https://github.com/mdtanker/polartoolkit/issues
Project-URL: Discussions, https://github.com/mdtanker/polartoolkit/discussions
Project-URL: Changelog, https://polartoolkit.readthedocs.io/en/latest/changelog.html
Author-email: Matt Tankersley <matt.d.tankersley@gmail.com>
License: The MIT License (MIT)
License-File: AUTHORS.md
License-File: LICENSE
Keywords: antarctica,arctic,cross-section,cryosphere,greenland,maps,plotting,pygmt
Classifier: Development Status :: 3 - Alpha
Classifier: Intended Audience :: Developers
Classifier: Intended Audience :: Education
Classifier: Intended Audience :: Science/Research
Classifier: License :: OSI Approved :: MIT License
Classifier: Natural Language :: English
Classifier: Operating System :: OS Independent
Classifier: Programming Language :: Python
Classifier: Programming Language :: Python :: 3
Classifier: Programming Language :: Python :: 3 :: Only
Classifier: Programming Language :: Python :: 3.11
Classifier: Programming Language :: Python :: 3.12
Classifier: Programming Language :: Python :: 3.13
Classifier: Topic :: Scientific/Engineering
Classifier: Typing :: Typed
Requires-Python: >=3.11
Requires-Dist: deprecation
Requires-Dist: earthaccess
Requires-Dist: geopandas>=1.0
Requires-Dist: harmonica>=0.6.0
Requires-Dist: numpy>=1.25.0
Requires-Dist: openpyxl
Requires-Dist: pandas>=2.0.0
Requires-Dist: pooch
Requires-Dist: pygmt>=0.10.0
Requires-Dist: pyogrio
Requires-Dist: pyproj
Requires-Dist: python-dotenv
Requires-Dist: requests
Requires-Dist: rioxarray
Requires-Dist: scipy>=1.11.0
Requires-Dist: tqdm
Requires-Dist: verde
Requires-Dist: xarray[io]>=2023.4.0
Requires-Dist: xrft
Requires-Dist: zarr>=3.0
